mcp_use/__init__.py
mcp_use/client.py
mcp_use/config.py
mcp_use/exceptions.py
mcp_use/logging.py
mcp_use/session.py
mcp_use/utils.py
mcp_use/adapters/.deprecated
mcp_use/adapters/__init__.py
mcp_use/adapters/base.py
mcp_use/adapters/langchain_adapter.py
mcp_use/agents/__init__.py
mcp_use/agents/base.py
mcp_use/agents/display.py
mcp_use/agents/mcpagent.py
mcp_use/agents/remote.py
mcp_use/agents/adapters/__init__.py
mcp_use/agents/adapters/anthropic.py
mcp_use/agents/adapters/base.py
mcp_use/agents/adapters/google.py
mcp_use/agents/adapters/langchain_adapter.py
mcp_use/agents/adapters/openai.py
mcp_use/agents/managers/__init__.py
mcp_use/agents/managers/base.py
mcp_use/agents/managers/server_manager.py
mcp_use/agents/managers/tools/__init__.py
mcp_use/agents/managers/tools/base_tool.py
mcp_use/agents/managers/tools/connect_server.py
mcp_use/agents/managers/tools/disconnect_server.py
mcp_use/agents/managers/tools/get_active_server.py
mcp_use/agents/managers/tools/list_servers_tool.py
mcp_use/agents/managers/tools/search_tools.py
mcp_use/agents/middleware/__init__.py
mcp_use/agents/middleware/tool_error_middleware.py
mcp_use/agents/observability/__init__.py
mcp_use/agents/observability/callbacks_manager.py
mcp_use/agents/observability/laminar.py
mcp_use/agents/observability/langfuse.py
mcp_use/agents/prompts/system_prompt_builder.py
mcp_use/agents/prompts/templates.py
mcp_use/auth/.deprecated
mcp_use/auth/__init__.py
mcp_use/auth/bearer.py
mcp_use/auth/oauth.py
mcp_use/auth/oauth_callback.py
mcp_use/client/__init__.py
mcp_use/client/client.py
mcp_use/client/code_executor.py
mcp_use/client/config.py
mcp_use/client/exceptions.py
mcp_use/client/prompts.py
mcp_use/client/session.py
mcp_use/client/auth/__init__.py
mcp_use/client/auth/bearer.py
mcp_use/client/auth/oauth.py
mcp_use/client/auth/oauth_callback.py
mcp_use/client/connectors/__init__.py
mcp_use/client/connectors/base.py
mcp_use/client/connectors/code_mode.py
mcp_use/client/connectors/http.py
mcp_use-1.5.1.dist-info/METADATA
mcp_use-1.5.1.dist-info/WHEEL
mcp_use-1.5.1.dist-info/RECORD
