Metadata-Version: 2.4
Name: mcp-use
Version: 1.5.1
Summary: MCP Library for LLMs
Author-email: "mcp-use, Inc." <dev@mcp-use.io>, Pietro Zullo <pietro.zullo@gmail.com>
License: MIT
Classifier: Development Status :: 3 - Alpha
Classifier: Intended Audience :: Developers
Classifier: License :: OSI Approved :: MIT License
Classifier: Operating System :: OS Independent
Classifier: Programming Language :: Python :: 3
Classifier: Programming Language :: Python :: 3.11
Classifier: Programming Language :: Python :: 3.12
Classifier: Topic :: Software Development :: Libraries :: Python Modules
Requires-Python: >=3.11
Requires-Dist: authlib>=1.0.0
Requires-Dist: httpx>=0.27.1
Requires-Dist: jsonschema-pydantic>=0.1.0
Requires-Dist: langchain>=1.0.0
Requires-Dist: mcp>=1.10.0
Requires-Dist: posthog>=3.0.0
Requires-Dist: pydantic<3.0.0,>=2.11.0
Requires-Dist: python-dotenv>=1.0.0
Requires-Dist: rich>=13.0.0
Requires-Dist: scarf-sdk>=0.1.0
Requires-Dist: websockets>=15.0
Provides-Extra: anthropic
Requires-Dist: langchain-anthropic; extra == 'anthropic'
Provides-Extra: dev
Requires-Dist: black>=23.9.0; extra == 'dev'
Requires-Dist: fastapi>=0.100.0; extra == 'dev'
Requires-Dist: isort>=5.12.0; extra == 'dev'
Requires-Dist: mypy>=1.5.0; extra == 'dev'
Requires-Dist: prek>=0.2.0; extra == 'dev'
Requires-Dist: pytest-asyncio>=1.3.0; extra == 'dev'
Requires-Dist: pytest-cov>=4.1.0; extra == 'dev'
Requires-Dist: pytest>=7.4.0; extra == 'dev'
Requires-Dist: ruff>=0.1.0; extra == 'dev'
Requires-Dist: ty>=0.0.1a7; extra == 'dev'
Provides-Extra: e2b
Requires-Dist: e2b-code-interpreter>=1.5.0; extra == 'e2b'
Provides-Extra: openai
Requires-Dist: langchain-openai; extra == 'openai'
Provides-Extra: search
Requires-Dist: fastembed>=0.3.0; extra == 'search'
